{"type":"FeatureCollection", "features": [
{"type":"Feature","geometry":{"type":"Point","coordinates":[121.3413475,31.1549935,18.013,-1.7976931348623157e+308]},"properties":{"OBJECTID":1,"DGID":"DG000001","SBLX":"车辆道杆","SBMC":"道杆01","PPMC":"","SBXH":"","SBZT":"在线","X":121.3413475,"Y":31.1549935,"Z":18.013,"WZ":"北门入口","XQID":"XQ000004","SQID":"SQ000001"}},
{"type":"Feature","geometry":{"type":"Point","coordinates":[121.34135,31.1549909,18.013,-1.7976931348623157e+308]},"properties":{"OBJECTID":2,"DGID":"DG000002","SBLX":"车辆道杆","SBMC":"道杆02","PPMC":"","SBXH":"","SBZT":"在线","X":121.34135,"Y":31.1549909,"Z":18.013,"WZ":"北门出口","XQID":"XQ000004","SQID":"SQ000001"}},
{"type":"Feature","geometry":{"type":"Point","coordinates":[121.341838,31.152985,18.013,-1.7976931348623157e+308]},"properties":{"OBJECTID":3,"DGID":"DG000003","SBLX":"车辆道杆","SBMC":"道杆03","PPMC":"","SBXH":"","SBZT":"在线","X":121.341838,"Y":31.152985,"Z":18.013,"WZ":"南门入口","XQID":"XQ000004","SQID":"SQ000001"}},
{"type":"Feature","geometry":{"type":"Point","coordinates":[121.3418402,31.1529811,18.013,-1.7976931348623157e+308]},"properties":{"OBJECTID":4,"DGID":"DG000004","SBLX":"车辆道杆","SBMC":"道杆04","PPMC":"","SBXH":"","SBZT":"在线","X":121.3418402,"Y":31.1529811,"Z":18.013,"WZ":"南门出口","XQID":"XQ000004","SQID":"SQ000001"}},
{"type":"Feature","geometry":{"type":"Point","coordinates":[121.3426024,31.1559093,18.013,-1.7976931348623157e+308]},"properties":{"OBJECTID":5,"DGID":"DG000005","SBLX":"车辆道杆","SBMC":"道杆05","PPMC":"","SBXH":"","SBZT":"离线","X":121.3426024,"Y":31.1559093,"Z":18.013,"WZ":"北门入口","XQID":"XQ000008","SQID":"SQ000001"}},
{"type":"Feature","geometry":{"type":"Point","coordinates":[121.3426106,31.155895,18.013,-1.7976931348623157e+308]},"properties":{"OBJECTID":6,"DGID":"DG000006","SBLX":"车辆道杆","SBMC":"道杆06","PPMC":"","SBXH":"","SBZT":"在线","X":121.3426106,"Y":31.155895,"Z":18.013,"WZ":"北门出口","XQID":"XQ000008","SQID":"SQ000001"}}
]}